{
	"kind": "method",
	"name": "postStory",
	"slug": "poststory",
	"description": "Posts a story on behalf of a managed business account. Requires the can_manage_stories business bot right",
	"parameters": [
		{
			"name": "business_connection_id",
			"type": {
				"kind": "string"
			},
			"required": true,
			"description": "Unique identifier of the business connection"
		},
		{
			"name": "content",
			"type": {
				"kind": "ref",
				"name": "InputStoryContent"
			},
			"required": true,
			"description": "Content of the story"
		},
		{
			"name": "active_period",
			"type": {
				"kind": "integer"
			},
			"required": true,
			"description": "Period after which the story is moved to the archive, in seconds; must be one of 6 * 3600, 12 * 3600, 86400, or 2 * 86400"
		},
		{
			"name": "caption",
			"type": {
				"kind": "string"
			},
			"required": false,
			"description": "Caption of the story, 0-2048 characters after entities parsing"
		},
		{
			"name": "parse_mode",
			"type": {
				"kind": "string"
			},
			"required": false,
			"description": "Mode for parsing entities in the story caption. See formatting options for more details."
		},
		{
			"name": "caption_entities",
			"type": {
				"kind": "array",
				"element": {
					"kind": "ref",
					"name": "MessageEntity"
				}
			},
			"required": false,
			"description": "A JSON-serialized list of special entities that appear in the caption, which can be specified instead of parse_mode"
		},
		{
			"name": "areas",
			"type": {
				"kind": "array",
				"element": {
					"kind": "ref",
					"name": "StoryArea"
				}
			},
			"required": false,
			"description": "A JSON-serialized list of clickable areas to be shown on the story"
		},
		{
			"name": "post_to_chat_page",
			"type": {
				"kind": "boolean"
			},
			"required": false,
			"description": "Pass True to keep the story accessible after it expires"
		},
		{
			"name": "protect_content",
			"type": {
				"kind": "boolean"
			},
			"required": false,
			"description": "Pass True if the content of the story must be protected from forwarding and screenshotting"
		}
	],
	"returns": {
		"kind": "ref",
		"name": "Story"
	}
}
